riffraff/__init__.py
riffraff/extrapolate.py
riffraff/riffle.py
riffraff-0.0.5.dist-info/LICENSE
riffraff-0.0.5.dist-info/METADATA
riffraff-0.0.5.dist-info/WHEEL
riffraff-0.0.5.dist-info/top_level.txt
riffraff-0.0.5.dist-info/RECORD
